datashack/__init__.py
datashack/cli/__init__.py
datashack/cli/__main__.py
datashack/cli/consts.py
datashack/cli/settings.py
datashack/cli/commands/__init__.py
datashack/cli/commands/stubs.py
datashack/cli/core/os.py
datashack/cli/core/loaders/__init__.py
datashack/cli/core/loaders/base.py
datashack/cli/core/loaders/python_loader.py
datashack/datashack_infra_app/.gitignore
datashack/datashack_infra_app/Pipfile
datashack/datashack_infra_app/Pipfile.lock
datashack/datashack_infra_app/__init__.py
datashack/datashack_infra_app/cdktf.json
datashack/datashack_infra_app/help
datashack/datashack_infra_app/main-test.py
datashack/datashack_infra_app/main.py
datashack/datashack_infra_app/manifest.json
datashack/datashack_infra_app/terraform.dev.tfstate
datashack/datashack_infra_app/terraform.dev.tfstate.backup
datashack/datashack_infra_app/triggers.py
datashack/datashack_infra_app/additional_plugins/__init__.py
datashack/datashack_infra_app/additional_plugins/datashack_base/__init__.py
datashack/datashack_infra_app/additional_plugins/datashack_base/datashack_base.py
datashack/datashack_infra_app/additional_plugins/datashack_glue/__init__.py
datashack/datashack_infra_app/additional_plugins/datashack_glue/datashack_glue.py
datashack/datashack_infra_app/additional_plugins/datashack_glue/utils/kinessis_stream_template
datashack/datashack_infra_app/additional_plugins/datashack_tf_module/main.tf
datashack/datashack_infra_app/additional_plugins/datashack_tf_module/variable.tf
datashack/utils/__init__.py
datashack/utils/console.py
datashack/utils/io.py
datashack/utils/py.py
datashack_sdk/__init__.py
datashack_sdk/athena.py
datashack_sdk/base.py
datashack_sdk/resource_config.py
datashack_sdk/resource_schemas.py
datashack-0.0.4.dist-info/METADATA
datashack-0.0.4.dist-info/WHEEL
datashack-0.0.4.dist-info/entry_points.txt
datashack-0.0.4.dist-info/top_level.txt
datashack-0.0.4.dist-info/RECORD
